shipyard_slack/__init__.py
shipyard_slack/slack.py
shipyard_slack/slack_utils.py
shipyard_slack/cli/__init__.py
shipyard_slack/cli/authtest.py
shipyard_slack/cli/send_conditional_message.py
shipyard_slack/cli/send_message.py
shipyard_slack/cli/send_message_with_file.py
shipyard_slack-0.1.7.dist-info/METADATA
shipyard_slack-0.1.7.dist-info/WHEEL
shipyard_slack-0.1.7.dist-info/top_level.txt
shipyard_slack-0.1.7.dist-info/RECORD
