Metadata-Version: 2.4
Name: shipyard-slack
Version: 0.1.7
Summary: A local client for connecting and working with Slack
Requires-Python: >=3.11
Requires-Dist: slack-sdk>=3.35.0
Requires-Dist: python-dotenv>=1.0.1
Requires-Dist: shipyard-bp-utils>=1.3.0
Requires-Dist: shipyard-templates>=0.6.2
